apache_superset_extensions_cli-0.0.1rc2.dist-info/licenses/LICENSE.txt
superset_extensions_cli/__init__.py
superset_extensions_cli/cli.py
superset_extensions_cli/constants.py
superset_extensions_cli/utils.py
superset_extensions_cli/templates/extension.json.j2
superset_extensions_cli/templates/backend/pyproject.toml.j2
superset_extensions_cli/templates/frontend/package.json.j2
apache_superset_extensions_cli-0.0.1rc2.dist-info/METADATA
apache_superset_extensions_cli-0.0.1rc2.dist-info/WHEEL
apache_superset_extensions_cli-0.0.1rc2.dist-info/entry_points.txt
apache_superset_extensions_cli-0.0.1rc2.dist-info/top_level.txt
apache_superset_extensions_cli-0.0.1rc2.dist-info/RECORD
