Metadata-Version: 2.4
Name: apache-superset-extensions-cli
Version: 0.0.1rc2
Summary: Official command-line interface for building, bundling, and managing Apache Superset extensions
Author-email: Apache Software Foundation <dev@superset.apache.org>
License:                               Apache License
Project-URL: Homepage, https://superset.apache.org/
Project-URL: Documentation, https://superset.apache.org/docs/
Project-URL: Repository, https://github.com/apache/superset
Project-URL: Bug Tracker, https://github.com/apache/superset/issues
Project-URL: Changelog, https://github.com/apache/superset/blob/master/CHANGELOG.md
Keywords: superset,apache,cli,extensions,analytics,business-intelligence,development-tools
Classifier: Development Status :: 3 - Alpha
Classifier: Environment :: Console
Classifier: Intended Audience :: Developers
Classifier: License :: OSI Approved :: Apache Software License
Classifier: Operating System :: OS Independent
Classifier: Programming Language :: Python :: 3
Classifier: Programming Language :: Python :: 3.10
Classifier: Programming Language :: Python :: 3.11
Classifier: Programming Language :: Python :: 3.12
Classifier: Topic :: Database
Classifier: Topic :: Scientific/Engineering :: Visualization
Classifier: Topic :: Software Development :: Build Tools
Classifier: Topic :: Software Development :: Libraries :: Python Modules
Classifier: Topic :: System :: Software Distribution
Requires-Python: >=3.10
License-File: LICENSE.txt
Requires-Dist: apache-superset-core
Requires-Dist: click>=8.0.3
Requires-Dist: jinja2>=3.1.6
Requires-Dist: semver>=3.0.4
Requires-Dist: tomli>=2.2.1; python_version < "3.11"
Requires-Dist: watchdog>=6.0.0
Provides-Extra: test
Requires-Dist: pytest; extra == "test"
Requires-Dist: pytest-cov; extra == "test"
Requires-Dist: pytest-mock; extra == "test"
Dynamic: license-file
